{
  "metadata": {
    "phase_name": "第三阶段 (第9-12周)",
    "phase_number": 3,
    "start_date": "2025-09-25",
    "end_date": "2025-10-22",
    "total_days": 28,
    "total_weeks": 4,
    "generation_time": "2025-09-25T08:57:44.690291"
  },
  "phase_info": {
    "name": "第三阶段 (第9-12周)",
    "description": "复杂语法结构",
    "focus": "语法深化",
    "grammar_topics": [
      "被动语态-基础用法",
      "定语从句-基础用法",
      "条件句-基础用法",
      "过去进行时-基础用法",
      "间接引语-基础用法"
    ],
    "word_level": "middle_school",
    "daily_words": 8,
    "exercises_per_day": 20
  },
  "weeks": [
    {
      "title": "第三阶段 (第9-12周) - 第1周",
      "start_date": "2025-09-25",
      "end_date": "2025-10-01",
      "days": [
        {
          "date": "2025-09-25",
          "day_name": "周一",
          "grammar_topic": "被动语态-基础用法",
          "word_count": 8,
          "exercise_count": 20,
          "word_level": "middle_school"
        },
        {
          "date": "2025-09-26",
          "day_name": "周二",
          "grammar_topic": "定语从句-基础用法",
          "word_count": 8,
          "exercise_count": 20,
          "word_level": "middle_school"
        },
        {
          "date": "2025-09-27",
          "day_name": "周三",
          "grammar_topic": "条件句-基础用法",
          "word_count": 8,
          "exercise_count": 20,
          "word_level": "middle_school"
        },
        {
          "date": "2025-09-28",
          "day_name": "周四",
          "grammar_topic": "过去进行时-基础用法",
          "word_count": 8,
          "exercise_count": 20,
          "word_level": "middle_school"
        },
        {
          "date": "2025-09-29",
          "day_name": "周五",
          "grammar_topic": "间接引语-基础用法",
          "word_count": 8,
          "exercise_count": 20,
          "word_level": "middle_school"
        },
        {
          "date": "2025-09-30",
          "day_name": "周六",
          "grammar_topic": "被动语态-基础用法",
          "word_count": 4,
          "exercise_count": 10,
          "word_level": "middle_school"
        },
        {
          "date": "2025-10-01",
          "day_name": "周日",
          "grammar_topic": "定语从句-基础用法",
          "word_count": 4,
          "exercise_count": 10,
          "word_level": "middle_school"
        }
      ],
      "total_words": 48,
      "total_exercises": 120
    },
    {
      "title": "第三阶段 (第9-12周) - 第2周",
      "start_date": "2025-10-02",
      "end_date": "2025-10-08",
      "days": [
        {
          "date": "2025-10-02",
          "day_name": "周一",
          "grammar_topic": "被动语态-基础用法",
          "word_count": 8,
          "exercise_count": 20,
          "word_level": "middle_school"
        },
        {
          "date": "2025-10-03",
          "day_name": "周二",
          "grammar_topic": "定语从句-基础用法",
          "word_count": 8,
          "exercise_count": 20,
          "word_level": "middle_school"
        },
        {
          "date": "2025-10-04",
          "day_name": "周三",
          "grammar_topic": "条件句-基础用法",
          "word_count": 8,
          "exercise_count": 20,
          "word_level": "middle_school"
        },
        {
          "date": "2025-10-05",
          "day_name": "周四",
          "grammar_topic": "过去进行时-基础用法",
          "word_count": 8,
          "exercise_count": 20,
          "word_level": "middle_school"
        },
        {
          "date": "2025-10-06",
          "day_name": "周五",
          "grammar_topic": "间接引语-基础用法",
          "word_count": 8,
          "exercise_count": 20,
          "word_level": "middle_school"
        },
        {
          "date": "2025-10-07",
          "day_name": "周六",
          "grammar_topic": "被动语态-基础用法",
          "word_count": 4,
          "exercise_count": 10,
          "word_level": "middle_school"
        },
        {
          "date": "2025-10-08",
          "day_name": "周日",
          "grammar_topic": "定语从句-基础用法",
          "word_count": 4,
          "exercise_count": 10,
          "word_level": "middle_school"
        }
      ],
      "total_words": 48,
      "total_exercises": 120
    },
    {
      "title": "第三阶段 (第9-12周) - 第3周",
      "start_date": "2025-10-09",
      "end_date": "2025-10-15",
      "days": [
        {
          "date": "2025-10-09",
          "day_name": "周一",
          "grammar_topic": "被动语态-基础用法",
          "word_count": 8,
          "exercise_count": 20,
          "word_level": "middle_school"
        },
        {
          "date": "2025-10-10",
          "day_name": "周二",
          "grammar_topic": "定语从句-基础用法",
          "word_count": 8,
          "exercise_count": 20,
          "word_level": "middle_school"
        },
        {
          "date": "2025-10-11",
          "day_name": "周三",
          "grammar_topic": "条件句-基础用法",
          "word_count": 8,
          "exercise_count": 20,
          "word_level": "middle_school"
        },
        {
          "date": "2025-10-12",
          "day_name": "周四",
          "grammar_topic": "过去进行时-基础用法",
          "word_count": 8,
          "exercise_count": 20,
          "word_level": "middle_school"
        },
        {
          "date": "2025-10-13",
          "day_name": "周五",
          "grammar_topic": "间接引语-基础用法",
          "word_count": 8,
          "exercise_count": 20,
          "word_level": "middle_school"
        },
        {
          "date": "2025-10-14",
          "day_name": "周六",
          "grammar_topic": "被动语态-基础用法",
          "word_count": 4,
          "exercise_count": 10,
          "word_level": "middle_school"
        },
        {
          "date": "2025-10-15",
          "day_name": "周日",
          "grammar_topic": "定语从句-基础用法",
          "word_count": 4,
          "exercise_count": 10,
          "word_level": "middle_school"
        }
      ],
      "total_words": 48,
      "total_exercises": 120
    },
    {
      "title": "第三阶段 (第9-12周) - 第4周",
      "start_date": "2025-10-16",
      "end_date": "2025-10-22",
      "days": [
        {
          "date": "2025-10-16",
          "day_name": "周一",
          "grammar_topic": "被动语态-基础用法",
          "word_count": 8,
          "exercise_count": 20,
          "word_level": "middle_school"
        },
        {
          "date": "2025-10-17",
          "day_name": "周二",
          "grammar_topic": "定语从句-基础用法",
          "word_count": 8,
          "exercise_count": 20,
          "word_level": "middle_school"
        },
        {
          "date": "2025-10-18",
          "day_name": "周三",
          "grammar_topic": "条件句-基础用法",
          "word_count": 8,
          "exercise_count": 20,
          "word_level": "middle_school"
        },
        {
          "date": "2025-10-19",
          "day_name": "周四",
          "grammar_topic": "过去进行时-基础用法",
          "word_count": 8,
          "exercise_count": 20,
          "word_level": "middle_school"
        },
        {
          "date": "2025-10-20",
          "day_name": "周五",
          "grammar_topic": "间接引语-基础用法",
          "word_count": 8,
          "exercise_count": 20,
          "word_level": "middle_school"
        },
        {
          "date": "2025-10-21",
          "day_name": "周六",
          "grammar_topic": "被动语态-基础用法",
          "word_count": 4,
          "exercise_count": 10,
          "word_level": "middle_school"
        },
        {
          "date": "2025-10-22",
          "day_name": "周日",
          "grammar_topic": "定语从句-基础用法",
          "word_count": 4,
          "exercise_count": 10,
          "word_level": "middle_school"
        }
      ],
      "total_words": 48,
      "total_exercises": 120
    }
  ],
  "statistics": {
    "total_words": 192,
    "total_exercises": 480,
    "average_words_per_day": 6.9,
    "average_exercises_per_day": 17.1
  }
}